easy_postgres/__init__.py
easy_postgres/connection.py
easy_postgres/dictionary.py
easy_postgres/transaction.py
easy_postgres-0.0.14.dist-info/LICENSE
easy_postgres-0.0.14.dist-info/METADATA
easy_postgres-0.0.14.dist-info/WHEEL
easy_postgres-0.0.14.dist-info/top_level.txt
easy_postgres-0.0.14.dist-info/RECORD
