Metadata-Version: 2.1
Name: easy-postgres
Version: 0.0.14
Summary: Abstraction layer for PostgreSQL database manipulation based on the psycopg2 package
Home-page: http://github.com/natiiix/easy_postgres
Author: Ivo Meixner
Author-email: natiwastaken@gmail.com
License: MIT
Keywords: postgresql postgres pgsql psql database psycopg2 easy
Platform: UNKNOWN
Classifier: Programming Language :: Python :: 3
Classifier: License :: OSI Approved :: MIT License
Classifier: Operating System :: OS Independent
Classifier: Topic :: Database
Requires-Dist: psycopg2-binary
